extinst/__init__.py
extinst/installer.py
extinst-0.1.0.dist-info/licenses/LICENSE
tests/__init__.py
tests/test_installer.py
extinst-0.1.0.dist-info/METADATA
extinst-0.1.0.dist-info/WHEEL
extinst-0.1.0.dist-info/top_level.txt
extinst-0.1.0.dist-info/RECORD
