Metadata-Version: 2.4
Name: extinst
Version: 0.1.0
Summary: A Python module to automatically install Chrome extensions on Windows/Mac/Linux
Home-page: https://github.com/codete2/
Author: CodeTea
Author-email: codeteamail@gmail.com
Classifier: Programming Language :: Python :: 3
Classifier: License :: OSI Approved :: MIT License
Classifier: Operating System :: OS Independent
Classifier: Topic :: Internet :: WWW/HTTP :: Browsers
Requires-Python: >=3.6
License-File: LICENSE
Requires-Dist: requests
Dynamic: author
Dynamic: author-email
Dynamic: classifier
Dynamic: description
Dynamic: description-content-type
Dynamic: home-page
Dynamic: license-file
Dynamic: requires-dist
Dynamic: requires-python
Dynamic: summary
